rmet/__init__.py
rmet/batch_evaluator.py
rmet/gap.py
rmet/groups.py
rmet/metrics.py
rmet/type_helpers.py
rmet/user_feature.py
rmet-0.1.6.dist-info/licenses/LICENSE
rmet-0.1.6.dist-info/METADATA
rmet-0.1.6.dist-info/WHEEL
rmet-0.1.6.dist-info/top_level.txt
rmet-0.1.6.dist-info/RECORD
