Metadata-Version: 2.4
Name: rmet
Version: 0.1.6
Summary: A collection of common recommendation system metrics
Author-email: Christian Ganhör <author@example.com>
License-Expression: MIT
Project-URL: Homepage, https://github.com/tigxy/recommender-metrics
Project-URL: Issues, https://github.com/tigxy/recommender-metrics/issues
Classifier: Programming Language :: Python :: 3
Classifier: Operating System :: OS Independent
Requires-Python: >=3.6
License-File: LICENSE
Requires-Dist: numpy
Requires-Dist: scipy
Requires-Dist: natsort
Dynamic: license-file
